bgpstuff/__init__.py
bgpstuff/bgpstuff.py
bgpstuff-1.1.2.dist-info/LICENSE
bgpstuff-1.1.2.dist-info/METADATA
bgpstuff-1.1.2.dist-info/WHEEL
bgpstuff-1.1.2.dist-info/top_level.txt
bgpstuff-1.1.2.dist-info/RECORD
