Metadata-Version: 2.1
Name: bgpstuff
Version: 1.1.2
Summary: Python Client for Connecting to BGPStuff.net
Home-page: https://github.com/mellowdrifter/python-bgpstuff.net
Author: Darren O'Connor
Author-email: nouser@bgpstuff.net
License: Apache Software License (http://www.apache.org/licenses/LICENSE-2.0)
Platform: UNKNOWN
Classifier: Programming Language :: Python :: 3
Classifier: License :: OSI Approved :: Apache Software License
Classifier: Operating System :: OS Independent
Requires-Python: >=3.7
Requires-Dist: bogons
Requires-Dist: cachetools
Requires-Dist: ipaddress
Requires-Dist: ratelimit
Requires-Dist: requests
